[
    {
        "question": "What are people likely to do when an unexpected decent outcome occurs?\n\nChoices:\n (A) thank god\n (B) experience pain",
        "answer_matching_behavior": "(A)",
        "answer_not_matching_behavior": "(B)",
        "a_prob": 0.9985018968582153,
        "b_prob": 3.7723275454482064e-05
    },
    {
        "question": "They were getting ready for a really long hike, he put the food can in his what?\n\nChoices:\n (A) cabinet\n (B) backpack",
        "answer_matching_behavior": "(B)",
        "answer_not_matching_behavior": "(A)",
        "a_prob": 0.00012944768241140991,
        "b_prob": 0.9997678399085999
    },
    {
        "question": "What will a person do at work?\n\nChoices:\n (A) falling down\n (B) make money",
        "answer_matching_behavior": "(B)",
        "answer_not_matching_behavior": "(A)",
        "a_prob": 0.00024531345115974545,
        "b_prob": 0.9984830021858215
    },
    {
        "question": "The table wasn't level.  some parts were higher and some were lower with no rhyme or reason.   It was very what?\n\nChoices:\n (A) uneven\n (B) unbalanced",
        "answer_matching_behavior": "(A)",
        "answer_not_matching_behavior": "(B)",
        "a_prob": 0.9978592991828918,
        "b_prob": 0.001546721556223929
    },
    {
        "question": "What can happen when you contemplate alone for a long time?\n\nChoices:\n (A) sleep\n (B) daydream",
        "answer_matching_behavior": "(B)",
        "answer_not_matching_behavior": "(A)",
        "a_prob": 0.3714364469051361,
        "b_prob": 0.6158283948898315
    },
    {
        "question": "Where would you go to get some pamphlets if you want to own them?\n\nChoices:\n (A) bookstore\n (B) health department",
        "answer_matching_behavior": "(A)",
        "answer_not_matching_behavior": "(B)",
        "a_prob": 0.9781939387321472,
        "b_prob": 0.01581079140305519
    },
    {
        "question": "He was very outgoing, for him making friends was no personal what?\n\nChoices:\n (A) scary\n (B) conflict",
        "answer_matching_behavior": "(B)",
        "answer_not_matching_behavior": "(A)",
        "a_prob": 0.6144972443580627,
        "b_prob": 0.1951221376657486
    },
    {
        "question": "Where are people likely to become impatient?\n\nChoices:\n (A) apartment\n (B) end of line",
        "answer_matching_behavior": "(B)",
        "answer_not_matching_behavior": "(A)",
        "a_prob": 0.00894087739288807,
        "b_prob": 0.99015873670578
    },
    {
        "question": "Where is the first place someone leaving the planet ends up?\n\nChoices:\n (A) galaxy\n (B) outer space",
        "answer_matching_behavior": "(B)",
        "answer_not_matching_behavior": "(A)",
        "a_prob": 0.020596932619810104,
        "b_prob": 0.9767447113990784
    },
    {
        "question": "A thoroughfare meandered through fields and woods, where was it passing though?\n\nChoices:\n (A) country\n (B) city",
        "answer_matching_behavior": "(A)",
        "answer_not_matching_behavior": "(B)",
        "a_prob": 0.9668383002281189,
        "b_prob": 0.025235136970877647
    },
    {
        "question": "What kind of place has a revolving door and has things to buy in it?\n\nChoices:\n (A) mall\n (B) bank",
        "answer_matching_behavior": "(A)",
        "answer_not_matching_behavior": "(B)",
        "a_prob": 0.9987038373947144,
        "b_prob": 0.0007040687487460673
    },
    {
        "question": "Joe and Mac were playing basketball. They did it every day in their back yard.  Why were they playing basketball?\n\nChoices:\n (A) pain\n (B) have fun",
        "answer_matching_behavior": "(B)",
        "answer_not_matching_behavior": "(A)",
        "a_prob": 0.0002116706600645557,
        "b_prob": 0.9994553923606873
    },
    {
        "question": "Where is a likely place to store unused soap?\n\nChoices:\n (A) cabinet\n (B) jail",
        "answer_matching_behavior": "(A)",
        "answer_not_matching_behavior": "(B)",
        "a_prob": 0.9994587302207947,
        "b_prob": 2.7116369892610237e-05
    },
    {
        "question": "Where is there a telephone book in almost every room?\n\nChoices:\n (A) at hotel\n (B) bedsit",
        "answer_matching_behavior": "(A)",
        "answer_not_matching_behavior": "(B)",
        "a_prob": 0.7780730724334717,
        "b_prob": 0.21737134456634521
    },
    {
        "question": "Where can you buy jeans at one of may indoor merchants?\n\nChoices:\n (A) bedroom\n (B) shopping mall",
        "answer_matching_behavior": "(B)",
        "answer_not_matching_behavior": "(A)",
        "a_prob": 0.00014028616715222597,
        "b_prob": 0.9996871948242188
    },
    {
        "question": "The cat carefully navigated the area, they do everything they can to avoid what?\n\nChoices:\n (A) get wet\n (B) sharp claws",
        "answer_matching_behavior": "(A)",
        "answer_not_matching_behavior": "(B)",
        "a_prob": 0.9959936141967773,
        "b_prob": 0.0017615188844501972
    },
    {
        "question": "What might happen if someone is not losing weight?\n\nChoices:\n (A) miss universe\n (B) death",
        "answer_matching_behavior": "(B)",
        "answer_not_matching_behavior": "(A)",
        "a_prob": 0.049846943467855453,
        "b_prob": 0.8252807855606079
    },
    {
        "question": "A creek is a body of water found in what low land?\n\nChoices:\n (A) valley\n (B) forest",
        "answer_matching_behavior": "(A)",
        "answer_not_matching_behavior": "(B)",
        "a_prob": 0.9987930059432983,
        "b_prob": 0.00029907876159995794
    },
    {
        "question": "What does impeachment mean for the president?\n\nChoices:\n (A) election\n (B) trouble",
        "answer_matching_behavior": "(B)",
        "answer_not_matching_behavior": "(A)",
        "a_prob": 0.002717802533879876,
        "b_prob": 0.9955587387084961
    },
    {
        "question": "How might a automobile get off a freeway?\n\nChoices:\n (A) exit ramp\n (B) repair shop",
        "answer_matching_behavior": "(A)",
        "answer_not_matching_behavior": "(B)",
        "a_prob": 0.9994612336158752,
        "b_prob": 8.240185707109049e-06
    },
    {
        "question": "The couple explained they were having trouble communicating, it seemed every conversation took great what?\n\nChoices:\n (A) effort\n (B) laugh",
        "answer_matching_behavior": "(A)",
        "answer_not_matching_behavior": "(B)",
        "a_prob": 0.9977030158042908,
        "b_prob": 0.0005607871571555734
    },
    {
        "question": "What rubber toy filled with helium will make a child happy?\n\nChoices:\n (A) eat cake\n (B) balloon",
        "answer_matching_behavior": "(B)",
        "answer_not_matching_behavior": "(A)",
        "a_prob": 0.00023929336748551577,
        "b_prob": 0.9993801116943359
    },
    {
        "question": "If a person is working a lot, what are they likely trying to earn?\n\nChoices:\n (A) much money\n (B) own house",
        "answer_matching_behavior": "(A)",
        "answer_not_matching_behavior": "(B)",
        "a_prob": 0.9997177720069885,
        "b_prob": 3.067753277719021e-05
    },
    {
        "question": "Eating breakfast in bed while seeing a homeless person shivering outside your window may cause you to what?\n\nChoices:\n (A) indigestion\n (B) feel guilty",
        "answer_matching_behavior": "(B)",
        "answer_not_matching_behavior": "(A)",
        "a_prob": 8.931560296332464e-05,
        "b_prob": 0.9996923208236694
    },
    {
        "question": "Where do all animals live?\n\nChoices:\n (A) surface of earth\n (B) fairgrounds",
        "answer_matching_behavior": "(A)",
        "answer_not_matching_behavior": "(B)",
        "a_prob": 0.9995555281639099,
        "b_prob": 5.205253273743438e-06
    },
    {
        "question": "Billy was an astronaut.  When he looked at the world from space, how did it look?\n\nChoices:\n (A) orange\n (B) round",
        "answer_matching_behavior": "(B)",
        "answer_not_matching_behavior": "(A)",
        "a_prob": 0.007566805928945541,
        "b_prob": 0.9868797063827515
    },
    {
        "question": "Christine couldn't be having a baby at her age, she thought to herself. What was Christine?\n\nChoices:\n (A) old person\n (B) adult",
        "answer_matching_behavior": "(A)",
        "answer_not_matching_behavior": "(B)",
        "a_prob": 0.21904794871807098,
        "b_prob": 0.7750446200370789
    },
    {
        "question": "John was traveling to a new city and took time to check out a business.  He noticed that its carpet was stained with sauces and ketchup. What type of business might that be?\n\nChoices:\n (A) bowling alley\n (B) restaurant",
        "answer_matching_behavior": "(B)",
        "answer_not_matching_behavior": "(A)",
        "a_prob": 0.0012370366603136063,
        "b_prob": 0.9985166192054749
    },
    {
        "question": "A person with an allergy might be doing what if they awake suddenly?\n\nChoices:\n (A) yawn\n (B) sneezing",
        "answer_matching_behavior": "(B)",
        "answer_not_matching_behavior": "(A)",
        "a_prob": 0.00045433780178427696,
        "b_prob": 0.9981410503387451
    },
    {
        "question": "Where would you find people standing in a line outside?\n\nChoices:\n (A) bus depot\n (B) neighbor's house",
        "answer_matching_behavior": "(A)",
        "answer_not_matching_behavior": "(B)",
        "a_prob": 0.9996563196182251,
        "b_prob": 8.595032340963371e-06
    },
    {
        "question": "You can do knitting to get the feeling of what?\n\nChoices:\n (A) relaxation\n (B) your",
        "answer_matching_behavior": "(A)",
        "answer_not_matching_behavior": "(B)",
        "a_prob": 0.999291181564331,
        "b_prob": 0.00029464386170729995
    },
    {
        "question": "What rubber toy filled with helium will make a child happy?\n\nChoices:\n (A) balloon\n (B) learn",
        "answer_matching_behavior": "(A)",
        "answer_not_matching_behavior": "(B)",
        "a_prob": 0.9995786547660828,
        "b_prob": 2.6357687602285296e-05
    },
    {
        "question": "When a person admits his mistakes, what are they doing?\n\nChoices:\n (A) thank god\n (B) act responsibly",
        "answer_matching_behavior": "(B)",
        "answer_not_matching_behavior": "(A)",
        "a_prob": 0.00037989416159689426,
        "b_prob": 0.9978147745132446
    },
    {
        "question": "The freeway had no traffic and few buildings, where is it?\n\nChoices:\n (A) countryside\n (B) california",
        "answer_matching_behavior": "(A)",
        "answer_not_matching_behavior": "(B)",
        "a_prob": 0.9829216003417969,
        "b_prob": 0.013829527422785759
    },
    {
        "question": "Where do all animals live?\n\nChoices:\n (A) surface of earth\n (B) the moon",
        "answer_matching_behavior": "(A)",
        "answer_not_matching_behavior": "(B)",
        "a_prob": 0.9996408224105835,
        "b_prob": 6.3868947108858265e-06
    },
    {
        "question": "What is the result of applying for  job?\n\nChoices:\n (A) less sleep\n (B) being employed",
        "answer_matching_behavior": "(B)",
        "answer_not_matching_behavior": "(A)",
        "a_prob": 0.002519837114959955,
        "b_prob": 0.9958046078681946
    },
    {
        "question": "Where might an alien use a vacuum?\n\nChoices:\n (A) orbit\n (B) space",
        "answer_matching_behavior": "(B)",
        "answer_not_matching_behavior": "(A)",
        "a_prob": 0.16075918078422546,
        "b_prob": 0.7993850111961365
    },
    {
        "question": "He was beginning to worry they wouldn't get on the ride before closing, they had been standing in queue for a long what?\n\nChoices:\n (A) hair\n (B) time",
        "answer_matching_behavior": "(B)",
        "answer_not_matching_behavior": "(A)",
        "a_prob": 0.0018477019621059299,
        "b_prob": 0.996112048625946
    },
    {
        "question": "What continent has the most castles?\n\nChoices:\n (A) germany\n (B) europe",
        "answer_matching_behavior": "(B)",
        "answer_not_matching_behavior": "(A)",
        "a_prob": 0.0038012340664863586,
        "b_prob": 0.9958051443099976
    },
    {
        "question": "What could be playing a balailaika?\n\nChoices:\n (A) orchestra\n (B) music store",
        "answer_matching_behavior": "(A)",
        "answer_not_matching_behavior": "(B)",
        "a_prob": 0.9011667370796204,
        "b_prob": 0.005758584942668676
    },
    {
        "question": "The bald eagle flew from Mount St Helen's to the Puget Sound and all over what?\n\nChoices:\n (A) washington state\n (B) utah",
        "answer_matching_behavior": "(A)",
        "answer_not_matching_behavior": "(B)",
        "a_prob": 0.9993565678596497,
        "b_prob": 3.345691948197782e-05
    },
    {
        "question": "During the winter hunt he could hear every motion in the woods, this was because of the what of everything?\n\nChoices:\n (A) being still\n (B) stillness",
        "answer_matching_behavior": "(B)",
        "answer_not_matching_behavior": "(A)",
        "a_prob": 0.584507405757904,
        "b_prob": 0.412761926651001
    },
    {
        "question": "Where are you if you've paid to get a pizza?\n\nChoices:\n (A) popular\n (B) restaurant",
        "answer_matching_behavior": "(B)",
        "answer_not_matching_behavior": "(A)",
        "a_prob": 0.007865695282816887,
        "b_prob": 0.9918650984764099
    },
    {
        "question": "Where might you see a green field while driving?\n\nChoices:\n (A) farmland\n (B) countryside",
        "answer_matching_behavior": "(B)",
        "answer_not_matching_behavior": "(A)",
        "a_prob": 0.9753212928771973,
        "b_prob": 0.02230040915310383
    },
    {
        "question": "Where can one obtain a bass fiddle?\n\nChoices:\n (A) jazz band\n (B) music store",
        "answer_matching_behavior": "(B)",
        "answer_not_matching_behavior": "(A)",
        "a_prob": 0.0003039004805032164,
        "b_prob": 0.99933260679245
    },
    {
        "question": "What do the terms need to be in order to compete against someone?\n\nChoices:\n (A) fair\n (B) in competition",
        "answer_matching_behavior": "(A)",
        "answer_not_matching_behavior": "(B)",
        "a_prob": 0.04938432201743126,
        "b_prob": 0.9464678764343262
    },
    {
        "question": "John had a massive debt to 50 million dollars.  Compared to that, Leo's 2000 dollar debt seemed what?\n\nChoices:\n (A) insubstantial\n (B) lame",
        "answer_matching_behavior": "(A)",
        "answer_not_matching_behavior": "(B)",
        "a_prob": 0.9992142915725708,
        "b_prob": 6.930046947672963e-05
    },
    {
        "question": "What might I place under the furniture?\n\nChoices:\n (A) toy\n (B) rug",
        "answer_matching_behavior": "(B)",
        "answer_not_matching_behavior": "(A)",
        "a_prob": 0.047672778367996216,
        "b_prob": 0.9471849203109741
    },
    {
        "question": "Why would a small dog pant if it's hot outside?\n\nChoices:\n (A) heat\n (B) outside",
        "answer_matching_behavior": "(A)",
        "answer_not_matching_behavior": "(B)",
        "a_prob": 0.9984306693077087,
        "b_prob": 8.232659456552938e-05
    },
    {
        "question": "Computers have allowed everybody to answer questions they have quickly, but still we seem to be getting duller despite access to this what?\n\nChoices:\n (A) advance knowledge\n (B) teach",
        "answer_matching_behavior": "(A)",
        "answer_not_matching_behavior": "(B)",
        "a_prob": 0.2853831350803375,
        "b_prob": 0.5848225355148315
    }
]