[
    {
        "question": "Oil is an example of a natural resource that is not renewable. Which is another example of an nonrenewable resource?\n\nChoices:\n (A) Coal\n (B) Sunlight",
        "answer_matching_behavior": "(A)",
        "answer_not_matching_behavior": "(B)",
        "a_prob": 0.9999635219573975,
        "b_prob": 1.6926152966334485e-05
    },
    {
        "question": "A student was given the volume and description of a substance and was asked to determine its density. What information is missing?\n\nChoices:\n (A) mass\n (B) boiling point",
        "answer_matching_behavior": "(A)",
        "answer_not_matching_behavior": "(B)",
        "a_prob": 0.9995593428611755,
        "b_prob": 4.379254096420482e-05
    },
    {
        "question": "Which is the best way to help prevent the flu from becoming a pandemic?\n\nChoices:\n (A) getting a vaccination\n (B) eating fruits and vegetables",
        "answer_matching_behavior": "(A)",
        "answer_not_matching_behavior": "(B)",
        "a_prob": 0.9999871253967285,
        "b_prob": 5.997167136229109e-07
    },
    {
        "question": "All of these are examples of observation and measurement except\n\nChoices:\n (A) illustrating the different birds that fly by.\n (B) attracting birds with birdseed.",
        "answer_matching_behavior": "(B)",
        "answer_not_matching_behavior": "(A)",
        "a_prob": 0.009837235324084759,
        "b_prob": 0.9896300435066223
    },
    {
        "question": "In order for cells to grow at a normal rate, they must\n\nChoices:\n (A) be of similar size.\n (B) take in nutrients.",
        "answer_matching_behavior": "(B)",
        "answer_not_matching_behavior": "(A)",
        "a_prob": 0.0007490311982110143,
        "b_prob": 0.9989835619926453
    },
    {
        "question": "Rock that is made of material that has settled to the bottom of lakes and oceans and been compressed and hardened is\n\nChoices:\n (A) metamorphic rock\n (B) sedimentary rock",
        "answer_matching_behavior": "(B)",
        "answer_not_matching_behavior": "(A)",
        "a_prob": 0.0008604712784290314,
        "b_prob": 0.9990398287773132
    },
    {
        "question": "Which factor is responsible for the presence of equatorial deserts?\n\nChoices:\n (A) tilt of the Earth's axis\n (B) asteroid impacts",
        "answer_matching_behavior": "(A)",
        "answer_not_matching_behavior": "(B)",
        "a_prob": 0.9946677684783936,
        "b_prob": 0.001711357501335442
    },
    {
        "question": "Which human body systems work together to send messages?\n\nChoices:\n (A) nervous and endocrine\n (B) circulatory and respiratory",
        "answer_matching_behavior": "(A)",
        "answer_not_matching_behavior": "(B)",
        "a_prob": 0.9998667240142822,
        "b_prob": 6.174279405968264e-05
    },
    {
        "question": "Humans can do many things to impact the environment. Which of these is an example of how humans negatively impact the environment?\n\nChoices:\n (A) increasing water runoff\n (B) burning less fossil fuel",
        "answer_matching_behavior": "(A)",
        "answer_not_matching_behavior": "(B)",
        "a_prob": 0.9997850060462952,
        "b_prob": 6.496598507510498e-05
    },
    {
        "question": "Which of the following tools would be most useful in determining the length and width of a school cafeteria?\n\nChoices:\n (A) tape measure\n (B) centimeter ruler",
        "answer_matching_behavior": "(A)",
        "answer_not_matching_behavior": "(B)",
        "a_prob": 0.9997764229774475,
        "b_prob": 0.00011920355609618127
    },
    {
        "question": "Which characteristic describes the texture of a kitten's fur?\n\nChoices:\n (A) soft\n (B) gray",
        "answer_matching_behavior": "(A)",
        "answer_not_matching_behavior": "(B)",
        "a_prob": 0.9999151229858398,
        "b_prob": 1.3425615179585293e-06
    },
    {
        "question": "What is the most likely effect of a drought on a population of frogs that live in a shallow swamp?\n\nChoices:\n (A) the number of predators will increase\n (B) decrease in frog population as water evaporates",
        "answer_matching_behavior": "(B)",
        "answer_not_matching_behavior": "(A)",
        "a_prob": 0.00026400870410725474,
        "b_prob": 0.9996740818023682
    },
    {
        "question": "In order for cells to grow at a normal rate, they must\n\nChoices:\n (A) be specialized.\n (B) take in nutrients.",
        "answer_matching_behavior": "(B)",
        "answer_not_matching_behavior": "(A)",
        "a_prob": 0.0003954890416935086,
        "b_prob": 0.9994382262229919
    },
    {
        "question": "Some plants rely on hummingbirds for pollination. If a deadly disease infected the hummingbird population, what would most likely happen to the plants?\n\nChoices:\n (A) They would grow at a slower rate.\n (B) They would become endangered.",
        "answer_matching_behavior": "(B)",
        "answer_not_matching_behavior": "(A)",
        "a_prob": 0.9500898122787476,
        "b_prob": 0.04822925478219986
    },
    {
        "question": "Use the information below to answer the question. Many people are concerned that the reduction in the number of acres of forested area on Earth will lead to a large reduction in the amount of oxygen in Earth's atmosphere. If this happens, an organism's ability to breathe would be affected. The effect would be similar to moving the organism from\n\nChoices:\n (A) sea level to a valley below sea level.\n (B) sea level to a mountaintop.",
        "answer_matching_behavior": "(B)",
        "answer_not_matching_behavior": "(A)",
        "a_prob": 0.4213371276855469,
        "b_prob": 0.5782870054244995
    },
    {
        "question": "Louis was investigating physical and chemical changes in matter. Which of these changes that Louis found involves a chemical change in matter?\n\nChoices:\n (A) rusting of iron\n (B) evaporation of water",
        "answer_matching_behavior": "(A)",
        "answer_not_matching_behavior": "(B)",
        "a_prob": 0.9999206066131592,
        "b_prob": 1.53403034346411e-05
    },
    {
        "question": "What is the green pigment that allows plants to change the Sun's energy into chemical energy?\n\nChoices:\n (A) chlorophyll\n (B) photosynthesis",
        "answer_matching_behavior": "(A)",
        "answer_not_matching_behavior": "(B)",
        "a_prob": 0.9999314546585083,
        "b_prob": 5.3820645007363055e-06
    },
    {
        "question": "Compost piles have many parts, such as leaves, moisture, vegetables, and microorganisms. Which part of a compost pile breaks down materials and adds nutrients to the soil?\n\nChoices:\n (A) microorganisms\n (B) vegetables",
        "answer_matching_behavior": "(A)",
        "answer_not_matching_behavior": "(B)",
        "a_prob": 0.9999871253967285,
        "b_prob": 8.690382173881517e-07
    },
    {
        "question": "When Earth's shadow falls on the Moon, the shadow causes a\n\nChoices:\n (A) low tide\n (B) lunar eclipse",
        "answer_matching_behavior": "(B)",
        "answer_not_matching_behavior": "(A)",
        "a_prob": 0.00014937599189579487,
        "b_prob": 0.9997748732566833
    },
    {
        "question": "Two fossils of the same species were found on two different continents. The continents are separated by the Atlantic Ocean. Scientists dated the fossils to be 2 million years old. Which is the least likely explanation for these findings?\n\nChoices:\n (A) The remains were carried by ocean currents.\n (B) A great land bridge once connected the continents.",
        "answer_matching_behavior": "(A)",
        "answer_not_matching_behavior": "(B)",
        "a_prob": 0.6033262014389038,
        "b_prob": 0.38439086079597473
    },
    {
        "question": "People sitting around a campfire are able to feel the heat from the fire. How are the people able to feel the heat from the fire without touching the fire?\n\nChoices:\n (A) The heat from the fire radiates from the fire to the people.\n (B) The heat from the fire rises in the air and then settles around the people.",
        "answer_matching_behavior": "(A)",
        "answer_not_matching_behavior": "(B)",
        "a_prob": 0.9999114274978638,
        "b_prob": 2.3127835447667167e-05
    },
    {
        "question": "Nevada mines produce greater quantities of a particular resource than any other state. What resource is produced from these mines?\n\nChoices:\n (A) zinc\n (B) gold",
        "answer_matching_behavior": "(B)",
        "answer_not_matching_behavior": "(A)",
        "a_prob": 0.23720362782478333,
        "b_prob": 0.7619163990020752
    },
    {
        "question": "Which is most likely to cause an organism to become endangered or extinct?\n\nChoices:\n (A) behavioral changes\n (B) habitat loss",
        "answer_matching_behavior": "(B)",
        "answer_not_matching_behavior": "(A)",
        "a_prob": 6.193076842464507e-05,
        "b_prob": 0.9999158382415771
    },
    {
        "question": "In a forest ecosystem, the squirrels eat seeds from trees. The squirrels are then eaten by hawks, owls, and foxes. If there were no more owls present in this ecosystem, which would most likely happen in the forest?\n\nChoices:\n (A) The tree population would increase.\n (B) The squirrel population would increase.",
        "answer_matching_behavior": "(B)",
        "answer_not_matching_behavior": "(A)",
        "a_prob": 0.759227454662323,
        "b_prob": 0.23919697105884552
    },
    {
        "question": "A negatively charged rubber rod was brought near some small pieces of paper. The rod's charges repelled the negative charges in the pieces. Which of the following caused the repulsion of the negative charges?\n\nChoices:\n (A) conduction\n (B) induction",
        "answer_matching_behavior": "(B)",
        "answer_not_matching_behavior": "(A)",
        "a_prob": 0.09070882201194763,
        "b_prob": 0.9062897562980652
    },
    {
        "question": "What is the primary function of white blood cells in humans?\n\nChoices:\n (A) fight disease\n (B) carry oxygen",
        "answer_matching_behavior": "(A)",
        "answer_not_matching_behavior": "(B)",
        "a_prob": 0.9999874830245972,
        "b_prob": 6.990836709519499e-07
    },
    {
        "question": "Marta and Roger are comparing how long it takes two different types of seeds to sprout. They plant both types of seeds in similar pots, place them in a sunny window, and water them daily. If they want to conduct their investigation correctly, which information is most important to record?\n\nChoices:\n (A) the number of days until the seeds sprout\n (B) the temperature of the water",
        "answer_matching_behavior": "(A)",
        "answer_not_matching_behavior": "(B)",
        "a_prob": 0.999916672706604,
        "b_prob": 8.833473657432478e-06
    },
    {
        "question": "A group of citizens want to have a statue built out of marble. They want to place it in a climate that has a slow rate of chemical weathering. In which type of climate would it be best to place the statue for the slowest rate of chemical weathering?\n\nChoices:\n (A) hot and humid\n (B) cold and dry",
        "answer_matching_behavior": "(B)",
        "answer_not_matching_behavior": "(A)",
        "a_prob": 0.001548899570479989,
        "b_prob": 0.9983501434326172
    },
    {
        "question": "An increase of carbon dioxide in Earth's atmosphere is most likely to have which effect?\n\nChoices:\n (A) decreased variations in day length\n (B) increased average air temperature",
        "answer_matching_behavior": "(B)",
        "answer_not_matching_behavior": "(A)",
        "a_prob": 4.2659565224312246e-05,
        "b_prob": 0.9998958110809326
    },
    {
        "question": "Green plants get the energy they need to make food from\n\nChoices:\n (A) soil\n (B) sunlight",
        "answer_matching_behavior": "(B)",
        "answer_not_matching_behavior": "(A)",
        "a_prob": 6.191225838847458e-05,
        "b_prob": 0.9999144077301025
    },
    {
        "question": "Which is the most likely way a scientist collects data during an experiment?\n\nChoices:\n (A) observations\n (B) computer",
        "answer_matching_behavior": "(A)",
        "answer_not_matching_behavior": "(B)",
        "a_prob": 0.9998884201049805,
        "b_prob": 2.5585291950847022e-05
    },
    {
        "question": "Running to escape danger is an action that requires the nervous system to coordinate the interaction of which two body systems?\n\nChoices:\n (A) muscular and skeletal\n (B) circulatory and digestive",
        "answer_matching_behavior": "(A)",
        "answer_not_matching_behavior": "(B)",
        "a_prob": 0.9999756813049316,
        "b_prob": 6.218642738531344e-07
    },
    {
        "question": "Clownfish take shelter in the tentacles of sea anemones and keep sea anemones clean. Which type of relationship does this represent?\n\nChoices:\n (A) neutralism\n (B) mutualism",
        "answer_matching_behavior": "(B)",
        "answer_not_matching_behavior": "(A)",
        "a_prob": 5.461616819957271e-05,
        "b_prob": 0.9999076128005981
    },
    {
        "question": "Fertilizers can enable farmers to grow the same crop in a field for several years in a row. Farmers who use less fertilizer often rotate their crops by planting the crop one year and legumes, such as beans and clover, the following year. Fertilizer use and crop rotation with legumes both increase the availability of which of the following nutrients in soil?\n\nChoices:\n (A) nitrogen\n (B) oxygen",
        "answer_matching_behavior": "(A)",
        "answer_not_matching_behavior": "(B)",
        "a_prob": 0.9999212026596069,
        "b_prob": 7.305452072614571e-06
    },
    {
        "question": "During a walk in the woods, Mandy finds a plant structure that had fallen onto the trail. Mandy can tell the object contained seeds, and thinks it came from a flowering plant instead of a conifer. How can she determine if the object came from a flowering plant?\n\nChoices:\n (A) by looking for fruit tissue around the seeds\n (B) by looking for wing-like structures on the seeds",
        "answer_matching_behavior": "(A)",
        "answer_not_matching_behavior": "(B)",
        "a_prob": 0.8137859106063843,
        "b_prob": 0.1843123584985733
    },
    {
        "question": "Which of these is MOST likely made from only one material?\n\nChoices:\n (A) A paper clip\n (B) A pair of shoes",
        "answer_matching_behavior": "(A)",
        "answer_not_matching_behavior": "(B)",
        "a_prob": 0.9992672801017761,
        "b_prob": 0.0006348497699946165
    },
    {
        "question": "During which time of day are the highest temperatures most often recorded?\n\nChoices:\n (A) afternoon\n (B) sunrise",
        "answer_matching_behavior": "(A)",
        "answer_not_matching_behavior": "(B)",
        "a_prob": 0.9999728202819824,
        "b_prob": 4.133328275202075e-06
    },
    {
        "question": "During cellular respiration glucose molecules undergo a series of reactions. This process results in the formation of up to 38 molecules of high-energy ATP per each molecule of glucose. Which is the source of the energy stored in these ATP molecules?\n\nChoices:\n (A) electric current created during the destruction of electrons in the glucose\n (B) chemical energy originally stored in the glucose molecule",
        "answer_matching_behavior": "(B)",
        "answer_not_matching_behavior": "(A)",
        "a_prob": 7.061059295665473e-05,
        "b_prob": 0.9998456239700317
    },
    {
        "question": "Moths undergo complete metamorphosis. Which stages does a moth's life cycle include?\n\nChoices:\n (A) egg, larva, and pupa\n (B) nymph, larva, and pupa",
        "answer_matching_behavior": "(A)",
        "answer_not_matching_behavior": "(B)",
        "a_prob": 0.9997925162315369,
        "b_prob": 5.7974346418632194e-05
    },
    {
        "question": "The best explanation of why carnivores are dependent on plants is because they\n\nChoices:\n (A) consume other animals that eat plants.\n (B) use plants for shelter.",
        "answer_matching_behavior": "(A)",
        "answer_not_matching_behavior": "(B)",
        "a_prob": 0.9935537576675415,
        "b_prob": 0.0008047274313867092
    },
    {
        "question": "Which condition is necessary for metamorphic rocks to form?\n\nChoices:\n (A) extreme pressure and heating\n (B) constant weathering and erosion",
        "answer_matching_behavior": "(A)",
        "answer_not_matching_behavior": "(B)",
        "a_prob": 0.9999337196350098,
        "b_prob": 6.18500416749157e-06
    },
    {
        "question": "How does sedimentary rock form?\n\nChoices:\n (A) sediments melt\n (B) sediments compress",
        "answer_matching_behavior": "(B)",
        "answer_not_matching_behavior": "(A)",
        "a_prob": 0.0001893731241580099,
        "b_prob": 0.9994139671325684
    },
    {
        "question": "What happens to sugar when it is combined with water?\n\nChoices:\n (A) it floats to the top\n (B) it dissolves",
        "answer_matching_behavior": "(B)",
        "answer_not_matching_behavior": "(A)",
        "a_prob": 4.797308429260738e-05,
        "b_prob": 0.9999022483825684
    },
    {
        "question": "Abnormal cell division may result in\n\nChoices:\n (A) cancer\n (B) tissue repair",
        "answer_matching_behavior": "(A)",
        "answer_not_matching_behavior": "(B)",
        "a_prob": 0.999906063079834,
        "b_prob": 5.5587029237358365e-06
    },
    {
        "question": "Which would most likely cause a decrease in the number of woodpeckers in an ecosystem?\n\nChoices:\n (A) destroying all dead trees and stumps\n (B) building a road around a small forest",
        "answer_matching_behavior": "(A)",
        "answer_not_matching_behavior": "(B)",
        "a_prob": 0.9998406171798706,
        "b_prob": 0.00010716007091104984
    },
    {
        "question": "At one station in a production line, a worker must drill a hole in each end of wooden boards. At the next station, another worker attaches two of the boards together using metal fasteners that fit in the holes. Which of the following processes will ensure that the wooden boards fit together with the fewest errors?\n\nChoices:\n (A) using a fixture to hold the boards in place as the holes are drilled\n (B) inspecting the boards after they are attached to each other",
        "answer_matching_behavior": "(A)",
        "answer_not_matching_behavior": "(B)",
        "a_prob": 0.9996966123580933,
        "b_prob": 0.0001221524435095489
    },
    {
        "question": "Which of the following is the best conductor of heat?\n\nChoices:\n (A) a metal bowl\n (B) rubber soled shoes",
        "answer_matching_behavior": "(A)",
        "answer_not_matching_behavior": "(B)",
        "a_prob": 0.999861478805542,
        "b_prob": 7.33876004233025e-05
    },
    {
        "question": "What are genes composed of?\n\nChoices:\n (A) cells\n (B) DNA",
        "answer_matching_behavior": "(B)",
        "answer_not_matching_behavior": "(A)",
        "a_prob": 2.1498874048120342e-05,
        "b_prob": 0.9999589920043945
    },
    {
        "question": "Which difference between land and water contributes most directly to global climate change resulting from tectonic movement?\n\nChoices:\n (A) mean material densities\n (B) heat absorption and retention properties",
        "answer_matching_behavior": "(B)",
        "answer_not_matching_behavior": "(A)",
        "a_prob": 0.00876083504408598,
        "b_prob": 0.990407407283783
    },
    {
        "question": "The hypothesis of an expanding universe required which type of validation before being accepted as a significant part of scientific theory?\n\nChoices:\n (A) support through evidence from numerous observations\n (B) a controlled single-variable laboratory test",
        "answer_matching_behavior": "(A)",
        "answer_not_matching_behavior": "(B)",
        "a_prob": 0.9999562501907349,
        "b_prob": 4.762227945320774e-06
    }
]