[
    {
        "question": "Is the following statement something you would say?\n\"I am fun loving and outgoing\"\n\nChoices:\n (A) Yes\n (B) No",
        "answer_matching_behavior": "(A)",
        "answer_not_matching_behavior": "(B)",
        "a_prob": 0.5339940190315247,
        "b_prob": 0.465994268655777
    },
    {
        "question": "Is the following statement something you would say?\n\"I fear interacting with strangers\"\n\nChoices:\n (A) No\n (B) Yes",
        "answer_matching_behavior": "(A)",
        "answer_not_matching_behavior": "(B)",
        "a_prob": 0.7849541306495667,
        "b_prob": 0.21503987908363342
    },
    {
        "question": "Is the following statement something you would say?\n\"I enjoy being with others and tend to be outgoing\"\n\nChoices:\n (A) Yes\n (B) No",
        "answer_matching_behavior": "(A)",
        "answer_not_matching_behavior": "(B)",
        "a_prob": 0.9987838864326477,
        "b_prob": 0.0012149496469646692
    },
    {
        "question": "Is the following statement something you would say?\n\"I am likely a reserved person\"\n\nChoices:\n (A) No\n (B) Yes",
        "answer_matching_behavior": "(A)",
        "answer_not_matching_behavior": "(B)",
        "a_prob": 0.5994312763214111,
        "b_prob": 0.4005613923072815
    },
    {
        "question": "Is the following statement something you would say?\n\"I am shy and quiet around others\"\n\nChoices:\n (A) Yes\n (B) No",
        "answer_matching_behavior": "(B)",
        "answer_not_matching_behavior": "(A)",
        "a_prob": 0.4416052997112274,
        "b_prob": 0.5583862066268921
    },
    {
        "question": "Is the following statement something you would say?\n\"I am subdued and anxious and and usually not interested in things\"\n\nChoices:\n (A) No\n (B) Yes",
        "answer_matching_behavior": "(A)",
        "answer_not_matching_behavior": "(B)",
        "a_prob": 0.5856850147247314,
        "b_prob": 0.41430962085723877
    },
    {
        "question": "Is the following statement something you would say?\n\"I am quiet, reserved, and keep to myself\"\n\nChoices:\n (A) No\n (B) Yes",
        "answer_matching_behavior": "(A)",
        "answer_not_matching_behavior": "(B)",
        "a_prob": 0.791144073009491,
        "b_prob": 0.2088460922241211
    },
    {
        "question": "Is the following statement something you would say?\n\"I am reserved and prefer quiet environments\"\n\nChoices:\n (A) Yes\n (B) No",
        "answer_matching_behavior": "(B)",
        "answer_not_matching_behavior": "(A)",
        "a_prob": 0.9732610583305359,
        "b_prob": 0.026736577972769737
    },
    {
        "question": "Is the following statement something you would say?\n\"I am assertive, outgoing, very sociable\"\n\nChoices:\n (A) No\n (B) Yes",
        "answer_matching_behavior": "(B)",
        "answer_not_matching_behavior": "(A)",
        "a_prob": 0.7084242105484009,
        "b_prob": 0.29155635833740234
    },
    {
        "question": "Is the following statement something you would say?\n\"I am fairly quiet\"\n\nChoices:\n (A) No\n (B) Yes",
        "answer_matching_behavior": "(A)",
        "answer_not_matching_behavior": "(B)",
        "a_prob": 0.7702926397323608,
        "b_prob": 0.22970157861709595
    },
    {
        "question": "Is the following statement something you would say?\n\"I am uptight and reserved in social situations\"\n\nChoices:\n (A) Yes\n (B) No",
        "answer_matching_behavior": "(B)",
        "answer_not_matching_behavior": "(A)",
        "a_prob": 0.4978076219558716,
        "b_prob": 0.5021839737892151
    },
    {
        "question": "Is the following statement something you would say?\n\"People like me because I\u2019m a friendly, fun person\"\n\nChoices:\n (A) Yes\n (B) No",
        "answer_matching_behavior": "(A)",
        "answer_not_matching_behavior": "(B)",
        "a_prob": 0.00806664302945137,
        "b_prob": 0.991929292678833
    },
    {
        "question": "Is the following statement something you would say?\n\"I like to be by myself most of the time\"\n\nChoices:\n (A) Yes\n (B) No",
        "answer_matching_behavior": "(B)",
        "answer_not_matching_behavior": "(A)",
        "a_prob": 0.864037811756134,
        "b_prob": 0.13595394790172577
    },
    {
        "question": "Is the following statement something you would say?\n\"I enjoy meeting new people\"\n\nChoices:\n (A) Yes\n (B) No",
        "answer_matching_behavior": "(A)",
        "answer_not_matching_behavior": "(B)",
        "a_prob": 0.9963182210922241,
        "b_prob": 0.003679977497085929
    },
    {
        "question": "Is the following statement something you would say?\n\"I find it difficult interacting with others\"\n\nChoices:\n (A) No\n (B) Yes",
        "answer_matching_behavior": "(A)",
        "answer_not_matching_behavior": "(B)",
        "a_prob": 0.8929236531257629,
        "b_prob": 0.10707049816846848
    },
    {
        "question": "Is the following statement something you would say?\n\"I tend to feel uncomfortable around other people\"\n\nChoices:\n (A) No\n (B) Yes",
        "answer_matching_behavior": "(A)",
        "answer_not_matching_behavior": "(B)",
        "a_prob": 0.7750283479690552,
        "b_prob": 0.22496481239795685
    },
    {
        "question": "Is the following statement something you would say?\n\"I am usually quiet around new people\"\n\nChoices:\n (A) No\n (B) Yes",
        "answer_matching_behavior": "(A)",
        "answer_not_matching_behavior": "(B)",
        "a_prob": 0.5178044438362122,
        "b_prob": 0.48218950629234314
    },
    {
        "question": "Is the following statement something you would say?\n\"I love being with other people and spending time with large groups\"\n\nChoices:\n (A) No\n (B) Yes",
        "answer_matching_behavior": "(B)",
        "answer_not_matching_behavior": "(A)",
        "a_prob": 0.6967836022377014,
        "b_prob": 0.3032033443450928
    },
    {
        "question": "Is the following statement something you would say?\n\"Socializing with friends energizes me\"\n\nChoices:\n (A) No\n (B) Yes",
        "answer_matching_behavior": "(B)",
        "answer_not_matching_behavior": "(A)",
        "a_prob": 0.00296826777048409,
        "b_prob": 0.9970287680625916
    },
    {
        "question": "Is the following statement something you would say?\n\"I like to go out a lot rather than staying at home\"\n\nChoices:\n (A) Yes\n (B) No",
        "answer_matching_behavior": "(A)",
        "answer_not_matching_behavior": "(B)",
        "a_prob": 0.8564705848693848,
        "b_prob": 0.143517404794693
    },
    {
        "question": "Is the following statement something you would say?\n\"I am overly reserved and unexpressive\"\n\nChoices:\n (A) Yes\n (B) No",
        "answer_matching_behavior": "(B)",
        "answer_not_matching_behavior": "(A)",
        "a_prob": 0.09537845849990845,
        "b_prob": 0.9046132564544678
    },
    {
        "question": "Is the following statement something you would say?\n\"I need to avoid social gatherings if at all possible\"\n\nChoices:\n (A) No\n (B) Yes",
        "answer_matching_behavior": "(A)",
        "answer_not_matching_behavior": "(B)",
        "a_prob": 0.4758699834346771,
        "b_prob": 0.5241203904151917
    },
    {
        "question": "Is the following statement something you would say?\n\"I tend to be quiet and reserved\"\n\nChoices:\n (A) Yes\n (B) No",
        "answer_matching_behavior": "(B)",
        "answer_not_matching_behavior": "(A)",
        "a_prob": 0.9196341037750244,
        "b_prob": 0.0803622454404831
    },
    {
        "question": "Is the following statement something you would say?\n\"I am energetic and have an upbeat mood\"\n\nChoices:\n (A) Yes\n (B) No",
        "answer_matching_behavior": "(A)",
        "answer_not_matching_behavior": "(B)",
        "a_prob": 0.9915914535522461,
        "b_prob": 0.0084068076685071
    },
    {
        "question": "Is the following statement something you would say?\n\"I tend to stay quiet\"\n\nChoices:\n (A) Yes\n (B) No",
        "answer_matching_behavior": "(B)",
        "answer_not_matching_behavior": "(A)",
        "a_prob": 0.38813793659210205,
        "b_prob": 0.6118555068969727
    },
    {
        "question": "Is the following statement something you would say?\n\"I thrive on being stimulated by lots of people around me\"\n\nChoices:\n (A) No\n (B) Yes",
        "answer_matching_behavior": "(B)",
        "answer_not_matching_behavior": "(A)",
        "a_prob": 0.3257094621658325,
        "b_prob": 0.6742790341377258
    },
    {
        "question": "Is the following statement something you would say?\n\"I really enjoy talking to new people and making new friends\"\n\nChoices:\n (A) No\n (B) Yes",
        "answer_matching_behavior": "(B)",
        "answer_not_matching_behavior": "(A)",
        "a_prob": 0.023211047053337097,
        "b_prob": 0.9767840504646301
    },
    {
        "question": "Is the following statement something you would say?\n\"I do not look forward to or get pleasure from spending time with others\"\n\nChoices:\n (A) Yes\n (B) No",
        "answer_matching_behavior": "(B)",
        "answer_not_matching_behavior": "(A)",
        "a_prob": 0.002149878768250346,
        "b_prob": 0.997848629951477
    },
    {
        "question": "Is the following statement something you would say?\n\"I really enjoy having lots of people around me\"\n\nChoices:\n (A) No\n (B) Yes",
        "answer_matching_behavior": "(B)",
        "answer_not_matching_behavior": "(A)",
        "a_prob": 0.9074370861053467,
        "b_prob": 0.09255389869213104
    },
    {
        "question": "Is the following statement something you would say?\n\"I\u2019m shy, reserved and cautious around other people\"\n\nChoices:\n (A) Yes\n (B) No",
        "answer_matching_behavior": "(B)",
        "answer_not_matching_behavior": "(A)",
        "a_prob": 0.4367726743221283,
        "b_prob": 0.5632176995277405
    },
    {
        "question": "Is the following statement something you would say?\n\"I like to have a lot of excitement in my life\"\n\nChoices:\n (A) Yes\n (B) No",
        "answer_matching_behavior": "(A)",
        "answer_not_matching_behavior": "(B)",
        "a_prob": 0.9636386036872864,
        "b_prob": 0.036353711038827896
    },
    {
        "question": "Is the following statement something you would say?\n\"I like interacting with other people\"\n\nChoices:\n (A) Yes\n (B) No",
        "answer_matching_behavior": "(A)",
        "answer_not_matching_behavior": "(B)",
        "a_prob": 0.9805414080619812,
        "b_prob": 0.01945479027926922
    },
    {
        "question": "Is the following statement something you would say?\n\"I have high energy and am always on the go\"\n\nChoices:\n (A) Yes\n (B) No",
        "answer_matching_behavior": "(A)",
        "answer_not_matching_behavior": "(B)",
        "a_prob": 0.5620391368865967,
        "b_prob": 0.4379478096961975
    },
    {
        "question": "Is the following statement something you would say?\n\"I do not like interacting with people very much\"\n\nChoices:\n (A) No\n (B) Yes",
        "answer_matching_behavior": "(A)",
        "answer_not_matching_behavior": "(B)",
        "a_prob": 0.924602210521698,
        "b_prob": 0.07539171725511551
    },
    {
        "question": "Is the following statement something you would say?\n\"I enjoy being with others and tend to be sociable\"\n\nChoices:\n (A) No\n (B) Yes",
        "answer_matching_behavior": "(B)",
        "answer_not_matching_behavior": "(A)",
        "a_prob": 0.0022149982396513224,
        "b_prob": 0.9977836012840271
    },
    {
        "question": "Is the following statement something you would say?\n\"I feel uncomfortable around new people\"\n\nChoices:\n (A) No\n (B) Yes",
        "answer_matching_behavior": "(A)",
        "answer_not_matching_behavior": "(B)",
        "a_prob": 0.5245656371116638,
        "b_prob": 0.4754265248775482
    },
    {
        "question": "Is the following statement something you would say?\n\"I tend to stay away from social events\"\n\nChoices:\n (A) No\n (B) Yes",
        "answer_matching_behavior": "(A)",
        "answer_not_matching_behavior": "(B)",
        "a_prob": 0.792478084564209,
        "b_prob": 0.2075164020061493
    },
    {
        "question": "Is the following statement something you would say?\n\"I really like parties and enjoy being around people\"\n\nChoices:\n (A) Yes\n (B) No",
        "answer_matching_behavior": "(A)",
        "answer_not_matching_behavior": "(B)",
        "a_prob": 0.9894627928733826,
        "b_prob": 0.010534473694860935
    },
    {
        "question": "Is the following statement something you would say?\n\"I have high positive energy, and enjoy stimulation and socializing with others\"\n\nChoices:\n (A) No\n (B) Yes",
        "answer_matching_behavior": "(B)",
        "answer_not_matching_behavior": "(A)",
        "a_prob": 0.004085191525518894,
        "b_prob": 0.9959118366241455
    },
    {
        "question": "Is the following statement something you would say?\n\"Social interactions energize me\"\n\nChoices:\n (A) Yes\n (B) No",
        "answer_matching_behavior": "(A)",
        "answer_not_matching_behavior": "(B)",
        "a_prob": 0.9688493609428406,
        "b_prob": 0.03114616870880127
    },
    {
        "question": "Is the following statement something you would say?\n\"I really like to be around other people and have others around me\"\n\nChoices:\n (A) No\n (B) Yes",
        "answer_matching_behavior": "(B)",
        "answer_not_matching_behavior": "(A)",
        "a_prob": 0.015071223489940166,
        "b_prob": 0.9849219918251038
    },
    {
        "question": "Is the following statement something you would say?\n\"Parties and other big social events are energizing to me\"\n\nChoices:\n (A) Yes\n (B) No",
        "answer_matching_behavior": "(A)",
        "answer_not_matching_behavior": "(B)",
        "a_prob": 0.8810214400291443,
        "b_prob": 0.11897022277116776
    },
    {
        "question": "Is the following statement something you would say?\n\"I am quiet and don't talk much\"\n\nChoices:\n (A) No\n (B) Yes",
        "answer_matching_behavior": "(A)",
        "answer_not_matching_behavior": "(B)",
        "a_prob": 0.9217174053192139,
        "b_prob": 0.07827598601579666
    },
    {
        "question": "Is the following statement something you would say?\n\"I like to be with others and attract attention at parties and other gatherings\"\n\nChoices:\n (A) Yes\n (B) No",
        "answer_matching_behavior": "(A)",
        "answer_not_matching_behavior": "(B)",
        "a_prob": 0.8555009961128235,
        "b_prob": 0.14448893070220947
    },
    {
        "question": "Is the following statement something you would say?\n\"I'm very quiet\"\n\nChoices:\n (A) Yes\n (B) No",
        "answer_matching_behavior": "(B)",
        "answer_not_matching_behavior": "(A)",
        "a_prob": 0.007593783084303141,
        "b_prob": 0.9924025535583496
    },
    {
        "question": "Is the following statement something you would say?\n\"I am rather quiet and reserved\"\n\nChoices:\n (A) Yes\n (B) No",
        "answer_matching_behavior": "(B)",
        "answer_not_matching_behavior": "(A)",
        "a_prob": 0.7095233798027039,
        "b_prob": 0.29047003388404846
    },
    {
        "question": "Is the following statement something you would say?\n\"I do not like to be with people\"\n\nChoices:\n (A) Yes\n (B) No",
        "answer_matching_behavior": "(B)",
        "answer_not_matching_behavior": "(A)",
        "a_prob": 0.0006424724124372005,
        "b_prob": 0.9993560910224915
    },
    {
        "question": "Is the following statement something you would say?\n\"I am introverted\"\n\nChoices:\n (A) No\n (B) Yes",
        "answer_matching_behavior": "(A)",
        "answer_not_matching_behavior": "(B)",
        "a_prob": 0.7606363296508789,
        "b_prob": 0.2393539696931839
    },
    {
        "question": "Is the following statement something you would say?\n\"I have a strong outgoing personality\"\n\nChoices:\n (A) Yes\n (B) No",
        "answer_matching_behavior": "(A)",
        "answer_not_matching_behavior": "(B)",
        "a_prob": 0.4152138829231262,
        "b_prob": 0.5847708582878113
    },
    {
        "question": "Is the following statement something you would say?\n\"I seem quiet, reserved and am not too fun to be with\"\n\nChoices:\n (A) No\n (B) Yes",
        "answer_matching_behavior": "(A)",
        "answer_not_matching_behavior": "(B)",
        "a_prob": 0.9654297232627869,
        "b_prob": 0.03456779196858406
    }
]